google/ai/generativelanguage/__init__.py
google/ai/generativelanguage/gapic_version.py
google/ai/generativelanguage/py.typed
google/ai/generativelanguage_v1/__init__.py
google/ai/generativelanguage_v1/gapic_metadata.json
google/ai/generativelanguage_v1/gapic_version.py
google/ai/generativelanguage_v1/py.typed
google/ai/generativelanguage_v1/services/__init__.py
google/ai/generativelanguage_v1/services/generative_service/__init__.py
google/ai/generativelanguage_v1/services/generative_service/async_client.py
google/ai/generativelanguage_v1/services/generative_service/client.py
google/ai/generativelanguage_v1/services/generative_service/transports/__init__.py
google/ai/generativelanguage_v1/services/generative_service/transports/base.py
google/ai/generativelanguage_v1/services/generative_service/transports/grpc.py
google/ai/generativelanguage_v1/services/generative_service/transports/grpc_asyncio.py
google/ai/generativelanguage_v1/services/generative_service/transports/rest.py
google/ai/generativelanguage_v1/services/generative_service/transports/rest_base.py
google/ai/generativelanguage_v1/services/model_service/__init__.py
google/ai/generativelanguage_v1/services/model_service/async_client.py
google/ai/generativelanguage_v1/services/model_service/client.py
google/ai/generativelanguage_v1/services/model_service/pagers.py
google/ai/generativelanguage_v1/services/model_service/transports/__init__.py
google/ai/generativelanguage_v1/services/model_service/transports/base.py
google/ai/generativelanguage_v1/services/model_service/transports/grpc.py
google/ai/generativelanguage_v1/services/model_service/transports/grpc_asyncio.py
google/ai/generativelanguage_v1/services/model_service/transports/rest.py
google/ai/generativelanguage_v1/services/model_service/transports/rest_base.py
google/ai/generativelanguage_v1/types/__init__.py
google/ai/generativelanguage_v1/types/citation.py
google/ai/generativelanguage_v1/types/content.py
google_ai_generativelanguage-0.6.17.dist-info/LICENSE
google_ai_generativelanguage-0.6.17.dist-info/METADATA
google_ai_generativelanguage-0.6.17.dist-info/WHEEL
google_ai_generativelanguage-0.6.17.dist-info/top_level.txt
google_ai_generativelanguage-0.6.17.dist-info/RECORD
